[
  { "yardLine": -1, "yardLookup": 1, "startingPoint": 0.0083 },
  { "yardLine": -2, "yardLookup": 2, "startingPoint": 0.0248 },
  { "yardLine": -3, "yardLookup": 3, "startingPoint": 0.0424 },
  { "yardLine": -4, "yardLookup": 4, "startingPoint": 0.0639 },
  { "yardLine": -5, "yardLookup": 5, "startingPoint": 0.0816 },
  { "yardLine": -6, "yardLookup": 6, "startingPoint": 0.1033 },
  { "yardLine": -7, "yardLookup": 7, "startingPoint": 0.1264 },
  { "yardLine": -8, "yardLookup": 8, "startingPoint": 0.1512 },
  { "yardLine": -9, "yardLookup": 9, "startingPoint": 0.1778 },
  { "yardLine": -10, "yardLookup": 10, "startingPoint": 0.2061 },
  { "yardLine": -11, "yardLookup": 11, "startingPoint": 0.2364 },
  { "yardLine": -12, "yardLookup": 12, "startingPoint": 0.2687 },
  { "yardLine": -13, "yardLookup": 13, "startingPoint": 0.3032 },
  { "yardLine": -14, "yardLookup": 14, "startingPoint": 0.3399 },
  { "yardLine": -15, "yardLookup": 15, "startingPoint": 0.379 },
  { "yardLine": -16, "yardLookup": 16, "startingPoint": 0.4206 },
  { "yardLine": -17, "yardLookup": 17, "startingPoint": 0.4648 },
  { "yardLine": -18, "yardLookup": 18, "startingPoint": 0.5117 },
  { "yardLine": -19, "yardLookup": 19, "startingPoint": 0.5613 },
  { "yardLine": -20, "yardLookup": 20, "startingPoint": 0.6139 },
  { "yardLine": -21, "yardLookup": 21, "startingPoint": 0.6694 },
  { "yardLine": -22, "yardLookup": 22, "startingPoint": 0.728 },
  { "yardLine": -23, "yardLookup": 23, "startingPoint": 0.7896 },
  { "yardLine": -24, "yardLookup": 24, "startingPoint": 0.8543 },
  { "yardLine": -25, "yardLookup": 25, "startingPoint": 0.9222 },
  { "yardLine": -26, "yardLookup": 26, "startingPoint": 0.9932 },
  { "yardLine": -27, "yardLookup": 27, "startingPoint": 1.067 },
  { "yardLine": -28, "yardLookup": 28, "startingPoint": 1.144 },
  { "yardLine": -29, "yardLookup": 29, "startingPoint": 1.224 },
  { "yardLine": -30, "yardLookup": 30, "startingPoint": 1.307 },
  { "yardLine": -31, "yardLookup": 31, "startingPoint": 1.392 },
  { "yardLine": -32, "yardLookup": 32, "startingPoint": 1.48 },
  { "yardLine": -33, "yardLookup": 33, "startingPoint": 1.57 },
  { "yardLine": -34, "yardLookup": 34, "startingPoint": 1.663 },
  { "yardLine": -35, "yardLookup": 35, "startingPoint": 1.757 },
  { "yardLine": -36, "yardLookup": 36, "startingPoint": 1.852 },
  { "yardLine": -37, "yardLookup": 37, "startingPoint": 1.949 },
  { "yardLine": -38, "yardLookup": 38, "startingPoint": 2.046 },
  { "yardLine": -39, "yardLookup": 39, "startingPoint": 2.144 },
  { "yardLine": -40, "yardLookup": 40, "startingPoint": 2.24 },
  { "yardLine": -41, "yardLookup": 41, "startingPoint": 2.34 },
  { "yardLine": -42, "yardLookup": 42, "startingPoint": 2.438 },
  { "yardLine": -43, "yardLookup": 43, "startingPoint": 2.534 },
  { "yardLine": -44, "yardLookup": 44, "startingPoint": 2.629 },
  { "yardLine": -45, "yardLookup": 45, "startingPoint": 2.723 },
  { "yardLine": -46, "yardLookup": 46, "startingPoint": 2.815 },
  { "yardLine": -47, "yardLookup": 47, "startingPoint": 2.904 },
  { "yardLine": -48, "yardLookup": 48, "startingPoint": 2.991 },
  { "yardLine": -49, "yardLookup": 49, "startingPoint": 3.076 },
  { "yardLine": 50, "yardLookup": 50, "startingPoint": 3.158 },
  { "yardLine": 49, "yardLookup": 51, "startingPoint": 3.237 },
  { "yardLine": 48, "yardLookup": 52, "startingPoint": 3.313 },
  { "yardLine": 47, "yardLookup": 53, "startingPoint": 3.386 },
  { "yardLine": 46, "yardLookup": 54, "startingPoint": 3.456 },
  { "yardLine": 45, "yardLookup": 55, "startingPoint": 3.523 },
  { "yardLine": 44, "yardLookup": 56, "startingPoint": 3.587 },
  { "yardLine": 43, "yardLookup": 57, "startingPoint": 3.647 },
  { "yardLine": 42, "yardLookup": 58, "startingPoint": 3.7058 },
  { "yardLine": 41, "yardLookup": 59, "startingPoint": 3.759 },
  { "yardLine": 40, "yardLookup": 60, "startingPoint": 3.81 },
  { "yardLine": 39, "yardLookup": 61, "startingPoint": 3.859 },
  { "yardLine": 38, "yardLookup": 62, "startingPoint": 3.905 },
  { "yardLine": 37, "yardLookup": 63, "startingPoint": 3.948 },
  { "yardLine": 36, "yardLookup": 64, "startingPoint": 3.989 },
  { "yardLine": 35, "yardLookup": 65, "startingPoint": 4.027 },
  { "yardLine": 34, "yardLookup": 66, "startingPoint": 4.063 },
  { "yardLine": 33, "yardLookup": 67, "startingPoint": 4.096 },
  { "yardLine": 32, "yardLookup": 68, "startingPoint": 4.128 },
  { "yardLine": 31, "yardLookup": 69, "startingPoint": 4.158 },
  { "yardLine": 30, "yardLookup": 70, "startingPoint": 4.185 },
  { "yardLine": 29, "yardLookup": 71, "startingPoint": 4.211 },
  { "yardLine": 28, "yardLookup": 72, "startingPoint": 4.235 },
  { "yardLine": 27, "yardLookup": 73, "startingPoint": 4.258 },
  { "yardLine": 26, "yardLookup": 74, "startingPoint": 4.279 },
  { "yardLine": 25, "yardLookup": 75, "startingPoint": 4.299 },
  { "yardLine": 24, "yardLookup": 76, "startingPoint": 4.318 },
  { "yardLine": 23, "yardLookup": 77, "startingPoint": 4.336 },
  { "yardLine": 22, "yardLookup": 78, "startingPoint": 4.352 },
  { "yardLine": 21, "yardLookup": 79, "startingPoint": 4.367 },
  { "yardLine": 20, "yardLookup": 80, "startingPoint": 4.382 },
  { "yardLine": 19, "yardLookup": 81, "startingPoint": 4.395 },
  { "yardLine": 18, "yardLookup": 82, "startingPoint": 4.408 },
  { "yardLine": 17, "yardLookup": 83, "startingPoint": 4.42 },
  { "yardLine": 16, "yardLookup": 84, "startingPoint": 4.431 },
  { "yardLine": 15, "yardLookup": 85, "startingPoint": 4.441 },
  { "yardLine": 14, "yardLookup": 86, "startingPoint": 4.451 },
  { "yardLine": 13, "yardLookup": 87, "startingPoint": 4.461 },
  { "yardLine": 12, "yardLookup": 88, "startingPoint": 4.469 },
  { "yardLine": 11, "yardLookup": 89, "startingPoint": 4.478 },
  { "yardLine": 10, "yardLookup": 90, "startingPoint": 4.486 },
  { "yardLine": 9, "yardLookup": 91, "startingPoint": 4.494 },
  { "yardLine": 8, "yardLookup": 92, "startingPoint": 4.502 },
  { "yardLine": 7, "yardLookup": 93, "startingPoint": 4.51 },
  { "yardLine": 6, "yardLookup": 94, "startingPoint": 4.517 },
  { "yardLine": 5, "yardLookup": 95, "startingPoint": 4.523 },
  { "yardLine": 4, "yardLookup": 96, "startingPoint": 4.529 },
  { "yardLine": 3, "yardLookup": 97, "startingPoint": 4.534 },
  { "yardLine": 2, "yardLookup": 98, "startingPoint": 4.54 },
  { "yardLine": 1, "yardLookup": 99, "startingPoint": 4.545 },
  { "yardLine": 0, "yardLookup": 100, "startingPoint": 6.96 }
]
